pipeview/__init__.py
pipeview/cache.py
pipeview/ui.py
pipeviewapp-0.1.0.dist-info/METADATA
pipeviewapp-0.1.0.dist-info/WHEEL
pipeviewapp-0.1.0.dist-info/entry_points.txt
pipeviewapp-0.1.0.dist-info/top_level.txt
pipeviewapp-0.1.0.dist-info/RECORD
