Metadata-Version: 2.4
Name: pipeviewapp
Version: 0.1.0
Summary: An interactive TUI for piped data.
Author-email: manti-X <manti@bakaloli.eu>
License-Expression: MIT
Project-URL: Homepage, https://github.com/manti-X/PipeViewApp
Project-URL: Bug Tracker, https://github.com/manti-X/PipeViewApp/issues
Classifier: Programming Language :: Python :: 3
Classifier: Operating System :: OS Independent
Classifier: Topic :: Terminals
Classifier: Topic :: Utilities
Classifier: Environment :: Console
Classifier: Development Status :: 5 - Production/Stable
Requires-Python: >=3.7
Requires-Dist: textual
